Workbook
Name European_Bank: Cleaned_Data!$A$1:$N$10001
Name European_Bank: Raw_Data!$A$1:$N$10001

Sheet Raw_Data
A1: Year | B1: CustomerId | C1: Surname | D1: CreditScore | E1: Geography | F1: Gender | G1: Age | H1: Tenure | I1: Balance | J1: NumOfProducts | K1: HasCrCard | L1: IsActiveMember | M1: EstimatedSalary | N1: Exited
A2: 2025 | B2: 15634602 | C2: Hargrave | D2: 619 | E2: France | F2: Female | G2: 42 | H2: 2 | I2: 0 | J2: 1 | K2: 1 | L2: 1 | M2: 101348.88 | N2: 1
A3: 2025 | B3: 15647311 | C3: Hill | D3: 608 | E3: Spain | F3: Female | G3: 41 | H3: 1 | I3: 83807.86 | J3: 1 | K3: 0 | L3: 1 | M3: 112542.58 | N3: 0
A4: 2025 | B4: 15619304 | C4: Onio | D4: 502 | E4: France | F4: Female | G4: 42 | H4: 8 | I4: 159660.8 | J4: 3 | K4: 1 | L4: 0 | M4: 113931.57 | N4: 1
A5: 2025 | B5: 15701354 | C5: Boni | D5: 699 | E5: France | F5: Female | G5: 39 | H5: 1 | I5: 0 | J5: 2 | K5: 0 | L5: 0 | M5: 93826.63 | N5: 0
A6: 2025 | B6: 15737888 | C6: Mitchell | D6: 850 | E6: Spain | F6: Female | G6: 43 | H6: 2 | I6: 125510.82 | J6: 1 | K6: 1 | L6: 1 | M6: 79084.1 | N6: 0
A7: 2025 | B7: 15574012 | C7: Chu | D7: 645 | E7: Spain | F7: Male | G7: 44 | H7: 8 | I7: 113755.78 | J7: 2 | K7: 1 | L7: 0 | M7: 149756.71 | N7: 1
A8: 2025 | B8: 15592531 | C8: Bartlett | D8: 822 | E8: France | F8: Male | G8: 50 | H8: 7 | I8: 0 | J8: 2 | K8: 1 | L8: 1 | M8: 10062.8 | N8: 0
A9: 2025 | B9: 15656148 | C9: Obinna | D9: 376 | E9: Germany | F9: Female | G9: 29 | H9: 4 | I9: 115046.74 | J9: 4 | K9: 1 | L9: 0 | M9: 119346.88 | N9: 1
A10: 2025 | B10: 15792365 | C10: He | D10: 501 | E10: France | F10: Male | G10: 44 | H10: 4 | I10: 142051.07 | J10: 2 | K10: 0 | L10: 1 | M10: 74940.5 | N10: 0
A11: 2025 | B11: 15592389 | C11: H? | D11: 684 | E11: France | F11: Male | G11: 27 | H11: 2 | I11: 134603.88 | J11: 1 | K11: 1 | L11: 1 | M11: 71725.73 | N11: 0
A12: 2025 | B12: 15767821 | C12: Bearce | D12: 528 | E12: France | F12: Male | G12: 31 | H12: 6 | I12: 102016.72 | J12: 2 | K12: 0 | L12: 0 | M12: 80181.12 | N12: 0
A13: 2025 | B13: 15737173 | C13: Andrews | D13: 497 | E13: Spain | F13: Male | G13: 24 | H13: 3 | I13: 0 | J13: 2 | K13: 1 | L13: 0 | M13: 76390.01 | N13: 0
... A10001: 2025 | B10001: 15628319 | C10001: Walker | D10001: 792 | E10001: France | F10001: Female | G10001: 28 | H10001: 4 | I10001: 130142.79 | J10001: 1 | K10001: 1 | L10001: 0 | M10001: 38190.78 | N10001: 0

Sheet Cleaned_Data
A1: Year | B1: CustomerId | C1: Surname | D1: CreditScore | E1: Geography | F1: Gender | G1: Age | H1: Tenure | I1: Balance | J1: NumOfProducts | K1: HasCrCard | L1: IsActiveMember | M1: EstimatedSalary | N1: Exited | O1: =COUNTBLANK(N2:N10001) -> 0 | P1: =COUNTIF(A:A,A2) -> 10000 | Q1: Age_Group | R1: CreditScore_Group | S1: Balance_Group
A2: 2025 | B2: 15634602 | C2: Hargrave | D2: 619 | E2: France | F2: Female | G2: 42 | H2: 2 | I2: 0 | J2: 1 | K2: 1 | L2: 1 | M2: 101348.88 | N2: 1 | Q2: =IF(G2<=30,"18-30",IF(G2<=45,"31-45",IF(G2<=60,"46-60","60+"))) -> 31-45 | R2: =IF(D2<500,"Poor",IF(D2<=650,"Fair",IF(D2<=750,"Good","Excellent"))) -> Fair | S2: =IF(I2<50000,"0-50K",IF(I2<=100000,"50K-100K","100K+")) -> 0-50K
A3: 2025 | B3: 15647311 | C3: Hill | D3: 608 | E3: Spain | F3: Female | G3: 41 | H3: 1 | I3: 83807.86 | J3: 1 | K3: 0 | L3: 1 | M3: 112542.58 | N3: 0 | Q3: =IF(G3<=30,"18-30",IF(G3<=45,"31-45",IF(G3<=60,"46-60","60+"))) -> 31-45 | R3: =IF(D3<500,"Poor",IF(D3<=650,"Fair",IF(D3<=750,"Good","Excellent"))) -> Fair | S3: =IF(I3<50000,"0-50K",IF(I3<=100000,"50K-100K","100K+")) -> 50K-100K
A4: 2025 | B4: 15619304 | C4: Onio | D4: 502 | E4: France | F4: Female | G4: 42 | H4: 8 | I4: 159660.8 | J4: 3 | K4: 1 | L4: 0 | M4: 113931.57 | N4: 1 | Q4: =IF(G4<=30,"18-30",IF(G4<=45,"31-45",IF(G4<=60,"46-60","60+"))) -> 31-45 | R4: =IF(D4<500,"Poor",IF(D4<=650,"Fair",IF(D4<=750,"Good","Excellent"))) -> Fair | S4: =IF(I4<50000,"0-50K",IF(I4<=100000,"50K-100K","100K+")) -> 100K+
A5: 2025 | B5: 15701354 | C5: Boni | D5: 699 | E5: France | F5: Female | G5: 39 | H5: 1 | I5: 0 | J5: 2 | K5: 0 | L5: 0 | M5: 93826.63 | N5: 0 | Q5: =IF(G5<=30,"18-30",IF(G5<=45,"31-45",IF(G5<=60,"46-60","60+"))) -> 31-45 | R5: =IF(D5<500,"Poor",IF(D5<=650,"Fair",IF(D5<=750,"Good","Excellent"))) -> Good | S5: =IF(I5<50000,"0-50K",IF(I5<=100000,"50K-100K","100K+")) -> 0-50K
A6: 2025 | B6: 15737888 | C6: Mitchell | D6: 850 | E6: Spain | F6: Female | G6: 43 | H6: 2 | I6: 125510.82 | J6: 1 | K6: 1 | L6: 1 | M6: 79084.1 | N6: 0 | Q6: =IF(G6<=30,"18-30",IF(G6<=45,"31-45",IF(G6<=60,"46-60","60+"))) -> 31-45 | R6: =IF(D6<500,"Poor",IF(D6<=650,"Fair",IF(D6<=750,"Good","Excellent"))) -> Excellent | S6: =IF(I6<50000,"0-50K",IF(I6<=100000,"50K-100K","100K+")) -> 100K+
A7: 2025 | B7: 15574012 | C7: Chu | D7: 645 | E7: Spain | F7: Male | G7: 44 | H7: 8 | I7: 113755.78 | J7: 2 | K7: 1 | L7: 0 | M7: 149756.71 | N7: 1 | Q7: =IF(G7<=30,"18-30",IF(G7<=45,"31-45",IF(G7<=60,"46-60","60+"))) -> 31-45 | R7: =IF(D7<500,"Poor",IF(D7<=650,"Fair",IF(D7<=750,"Good","Excellent"))) -> Fair | S7: =IF(I7<50000,"0-50K",IF(I7<=100000,"50K-100K","100K+")) -> 100K+
A8: 2025 | B8: 15592531 | C8: Bartlett | D8: 822 | E8: France | F8: Male | G8: 50 | H8: 7 | I8: 0 | J8: 2 | K8: 1 | L8: 1 | M8: 10062.8 | N8: 0 | Q8: =IF(G8<=30,"18-30",IF(G8<=45,"31-45",IF(G8<=60,"46-60","60+"))) -> 46-60 | R8: =IF(D8<500,"Poor",IF(D8<=650,"Fair",IF(D8<=750,"Good","Excellent"))) -> Excellent | S8: =IF(I8<50000,"0-50K",IF(I8<=100000,"50K-100K","100K+")) -> 0-50K
A9: 2025 | B9: 15656148 | C9: Obinna | D9: 376 | E9: Germany | F9: Female | G9: 29 | H9: 4 | I9: 115046.74 | J9: 4 | K9: 1 | L9: 0 | M9: 119346.88 | N9: 1 | Q9: =IF(G9<=30,"18-30",IF(G9<=45,"31-45",IF(G9<=60,"46-60","60+"))) -> 18-30 | R9: =IF(D9<500,"Poor",IF(D9<=650,"Fair",IF(D9<=750,"Good","Excellent"))) -> Poor | S9: =IF(I9<50000,"0-50K",IF(I9<=100000,"50K-100K","100K+")) -> 100K+
A10: 2025 | B10: 15792365 | C10: He | D10: 501 | E10: France | F10: Male | G10: 44 | H10: 4 | I10: 142051.07 | J10: 2 | K10: 0 | L10: 1 | M10: 74940.5 | N10: 0 | Q10: =IF(G10<=30,"18-30",IF(G10<=45,"31-45",IF(G10<=60,"46-60","60+"))) -> 31-45 | R10: =IF(D10<500,"Poor",IF(D10<=650,"Fair",IF(D10<=750,"Good","Excellent"))) -> Fair | S10: =IF(I10<50000,"0-50K",IF(I10<=100000,"50K-100K","100K+")) -> 100K+
A11: 2025 | B11: 15592389 | C11: H? | D11: 684 | E11: France | F11: Male | G11: 27 | H11: 2 | I11: 134603.88 | J11: 1 | K11: 1 | L11: 1 | M11: 71725.73 | N11: 0 | Q11: =IF(G11<=30,"18-30",IF(G11<=45,"31-45",IF(G11<=60,"46-60","60+"))) -> 18-30 | R11: =IF(D11<500,"Poor",IF(D11<=650,"Fair",IF(D11<=750,"Good","Excellent"))) -> Good | S11: =IF(I11<50000,"0-50K",IF(I11<=100000,"50K-100K","100K+")) -> 100K+
A12: 2025 | B12: 15767821 | C12: Bearce | D12: 528 | E12: France | F12: Male | G12: 31 | H12: 6 | I12: 102016.72 | J12: 2 | K12: 0 | L12: 0 | M12: 80181.12 | N12: 0 | Q12: =IF(G12<=30,"18-30",IF(G12<=45,"31-45",IF(G12<=60,"46-60","60+"))) -> 31-45 | R12: =IF(D12<500,"Poor",IF(D12<=650,"Fair",IF(D12<=750,"Good","Excellent"))) -> Fair | S12: =IF(I12<50000,"0-50K",IF(I12<=100000,"50K-100K","100K+")) -> 100K+
A13: 2025 | B13: 15737173 | C13: Andrews | D13: 497 | E13: Spain | F13: Male | G13: 24 | H13: 3 | I13: 0 | J13: 2 | K13: 1 | L13: 0 | M13: 76390.01 | N13: 0 | Q13: =IF(G13<=30,"18-30",IF(G13<=45,"31-45",IF(G13<=60,"46-60","60+"))) -> 18-30 | R13: =IF(D13<500,"Poor",IF(D13<=650,"Fair",IF(D13<=750,"Good","Excellent"))) -> Poor | S13: =IF(I13<50000,"0-50K",IF(I13<=100000,"50K-100K","100K+")) -> 0-50K
... A10001: 2025 | B10001: 15628319 | C10001: Walker | D10001: 792 | E10001: France | F10001: Female | G10001: 28 | H10001: 4 | I10001: 130142.79 | J10001: 1 | K10001: 1 | L10001: 0 | M10001: 38190.78 | N10001: 0 | Q10001: =IF(G10001<=30,"18-30",IF(G10001<=45,"31-45",IF(G10001<=60,"46-60","60+"))) -> 18-30 | R10001: =IF(D10001<500,"Poor",IF(D10001<=650,"Fair",IF(D10001<=750,"Good","Excellent"))) -> Excellent | S10001: =IF(I10001<50000,"0-50K",IF(I10001<=100000,"50K-100K","100K+")) -> 100K+

Sheet Pivot_Table
A1: Row Labels | B1: Sum of Exited | G1: Row Labels | H1: Sum of Exited | M1: Row Labels | N1: Sum of Exited
A2: France | B2: 5014 | G2: 0 | H2: 413 | M2: Excellent | N2: 1598
A3: Germany | B3: 2509 | G3: 1 | H3: 1035 | M3: Fair | N3: 4305
A4: Spain | B4: 2477 | G4: 2 | H4: 1048 | M4: Good | N4: 3465
A5: Grand Total | B5: 10000 | G5: 3 | H5: 1009 | M5: Poor | N5: 632
G6: 4 | H6: 989 | M6: Grand Total | N6: 10000
A7: Row Labels | B7: Sum of Exited | G7: 5 | H7: 1012
A8: Female | B8: 4543 | G8: 6 | H8: 967 | M8: Row Labels | N8: Sum of Exited
A9: Male | B9: 5457 | G9: 7 | H9: 1028 | M9: 0-50K | N9: 3692
A10: Grand Total | B10: 10000 | G10: 8 | H10: 1025 | M10: 100K+ | N10: 4799
G11: 9 | H11: 984 | M11: 50K-100K | N11: 1509
A12: Row Labels | B12: Sum of Exited | G12: 10 | H12: 490 | M12: Grand Total | N12: 10000
A13: 18-30 | B13: 1968 | G13: Grand Total | H13: 10000
A14: 31-45 | B14: 5921 | M14: Row Labels | N14: Sum of Exited
A15: 46-60 | B15: 1647 | G15: Row Labels | H15: Sum of Exited | M15: 0 | N15: 4849
A16: 60+ | B16: 464 | G16: 1 | H16: 5084 | M16: 1 | N16: 5151
A17: Grand Total | B17: 10000 | G17: 2 | H17: 4590 | M17: Grand Total | N17: 10000
G18: 3 | H18: 266
A19: Row Labels | B19: Sum of Exited | G19: 4 | H19: 60
A20: 0 | B20: 2945 | G20: Grand Total | H20: 10000
A21: 1 | B21: 7055
A22: Grand Total | B22: 10000

Sheet Dashboard
E3: Bank Customer Churn Analysis Dashboard
B5: Total Customer | E5: Churned Customers | I5: Retained Customers | M5: Average Balance | Q5: Active Member
B6: =COUNTA(Cleaned_Data!B2:B10001) -> 10000 | F6: =COUNTIF(Cleaned_Data!N2:N10001,1) -> 2037 | J6: =COUNTIF(Cleaned_Data!N2:N10001,0) -> 7963 | N6: =AVERAGE(Cleaned_Data!I2:I10001) -> 76485.889 | R6: =COUNTIF(Cleaned_Data!L2:L10001,1) -> 5151
B19: France contributes the highest number of churned | H19: Customers aged 31-45 contribute to a major portion of | N19: Higher balance customers leaving may result in
B20: customers. | H20: churn cases. | N20: substantial revenue loss.
O21: Recommendations
N22: (i) Focus retention campaigns on customers in the Fair and
N23: Good credit score segments, as they contribute the highest
N24: churn counts.
N26: (ii) Introduce personalized loyalty offers for customers with
N27: higher account balances to reduce potential revenue loss.
N29: (iii) Develop targeted engagement strategies for customers aged
N30: 31-45, since this group contributes heavily to churn.
N32: (iv) Encourage customers to use multiple banking products
N33: through bundled offers and reward programs.
B35: Customers with fewer banking products tend to churn | H35: Fair and Good credit score segments contribute the | N35: (v) Strengthen customer relationship programs in high-churn
B36: frequently. | H36: highest churn counts. | N36: geographic regions.
